ferriswheel/__init__.py
ferriswheel/guild.py
ferriswheel-0.1.dist-info/LICENSE
ferriswheel-0.1.dist-info/METADATA
ferriswheel-0.1.dist-info/WHEEL
ferriswheel-0.1.dist-info/top_level.txt
ferriswheel-0.1.dist-info/RECORD
