Metadata-Version: 2.1
Name: ferriswheel
Version: 0.1
Summary: https://ferris.chat API library
Home-page: http://github.com/randomairborne/ferriswheel
Author: valkyrie_pilot
Author-email: valk@randomairborne.dev
License: LGPL
Project-URL: Bug Tracker, https://github.com/randomairborne/ferriswheel
Platform: UNKNOWN
Classifier: Programming Language :: Python :: 3
Classifier: License :: OSI Approved :: MIT License
Classifier: Operating System :: OS Independent
Requires-Python: >=3.6
License-File: LICENSE
Requires-Dist: emoji
